{
  "eventos": [
    {
      "titulo": "Curso Bootstrap",
      "data": "26/04/2018",
      "horaInicio": "15:00",
      "horaFim": "17:00",
      "descricao": "Apresentação do conceito de Grid e principais funcionalidades",
      "id": 1
    },
    {
      "titulo": "Imersão Angular",
      "data": "19/07/2018",
      "horaInicio": "15:00",
      "horaFim": "19:00",
      "descricao": "Ferramentas poderosas do angular 5",
      "id": 2
    },
    {
      "titulo": "Dia das mães",
      "data": "12/05/2018",
      "horaInicio": "09:00",
      "horaFim": "12:00",
      "descricao": "Festa do dia das mães",
      "id": 3
    },
    {
      "titulo": "Trocando horario",
      "data": "28/07/2018",
      "horaInicio": "00:00",
      "horaFim": "01:00",
      "descricao": "Troca de horários no servidores",
      "id": 4
    },
    {
      "titulo": "Outro teste",
      "data": "19/05/2018",
      "horaInicio": "10:59",
      "horaFim": "11:59",
      "descricao": "testando",
      "id": 6
    },
    {
      "titulo": "Teste",
      "data": "21/09/2018",
      "horaInicio": "10:00",
      "horaFim": "10:20",
      "descricao": "Testando",
      "id": 7
    },
    {
      "titulo": "teste de novo",
      "data": "09/09/2018",
      "horaInicio": "10:00",
      "horaFim": "11:00",
      "descricao": "teste",
      "id": 8
    },
    {
      "titulo": "Gerando novo evento",
      "data": "26/09/2018",
      "horaInicio": "11:30",
      "horaFim": "12:30",
      "descricao": "Gerando um teste simples",
      "id": 9
    }
  ],
  "login": [
    {
      "id": 1,
      "email": "kaleopiasse@gmail.com",
      "senha": "123456"
    }
  ]
}